FCLogger.py
FuzzyClassificator.py
FuzzyRoutines.py
LICENSE
PyBrainLearning.py
README.md
__init__.py
candidates.dat
classification_process.png
classification_process.pyuml
ethalons.dat
network.xml
report.txt
pybrain/__init__.py
pybrain/utilities.py
pybrain/auxiliary/__init__.py
pybrain/auxiliary/gaussprocess.py
pybrain/auxiliary/gradientdescent.py
pybrain/auxiliary/importancemixing.py
pybrain/auxiliary/kmeans.py
pybrain/auxiliary/pca.py
pybrain/datasets/__init__.py
pybrain/datasets/classification.py
pybrain/datasets/dataset.py
pybrain/datasets/importance.py
pybrain/datasets/reinforcement.py
pybrain/datasets/sequential.py
pybrain/datasets/supervised.py
pybrain/datasets/unsupervised.py
pybrain/optimization/__init__.py
pybrain/optimization/hillclimber.py
pybrain/optimization/neldermead.py
pybrain/optimization/optimizer.py
pybrain/optimization/randomsearch.py
pybrain/optimization/distributionbased/__init__.py
pybrain/optimization/distributionbased/cmaes.py
pybrain/optimization/distributionbased/distributionbased.py
pybrain/optimization/distributionbased/fem.py
pybrain/optimization/distributionbased/nes.py
pybrain/optimization/distributionbased/rank1.py
pybrain/optimization/distributionbased/snes.py
pybrain/optimization/distributionbased/ves.py
pybrain/optimization/distributionbased/xnes.py
pybrain/optimization/finitedifference/__init__.py
pybrain/optimization/finitedifference/fd.py
pybrain/optimization/finitedifference/pgpe.py
pybrain/optimization/finitedifference/spsa.py
pybrain/optimization/memetic/__init__.py
pybrain/optimization/memetic/innerinversememetic.py
pybrain/optimization/memetic/innermemetic.py
pybrain/optimization/memetic/inversememetic.py
pybrain/optimization/memetic/memetic.py
pybrain/optimization/populationbased/__init__.py
pybrain/optimization/populationbased/es.py
pybrain/optimization/populationbased/evolution.py
pybrain/optimization/populationbased/ga.py
pybrain/optimization/populationbased/pso.py
FuzzyClassificator-1.3.84.dist-info/LICENSE
FuzzyClassificator-1.3.84.dist-info/METADATA
FuzzyClassificator-1.3.84.dist-info/WHEEL
FuzzyClassificator-1.3.84.dist-info/entry_points.txt
FuzzyClassificator-1.3.84.dist-info/top_level.txt
FuzzyClassificator-1.3.84.dist-info/zip-safe
FuzzyClassificator-1.3.84.dist-info/RECORD
