Metadata-Version: 2.1
Name: FuzzyClassificator
Version: 1.3.84
Summary: This program uses neural networks to solve classification problems, and uses fuzzy sets and fuzzy logic to interpreting results.
Home-page: https://devopshq.github.io/FuzzyClassificator/
Author: Timur Gilmullin
Author-email: tim55667757@gmail.com
License: MIT
Download-URL: https://github.com/devopshq/FuzzyClassificator.git
Keywords: classificating,clustering,classificator,fuzzy,logic,math,science,research
Platform: UNKNOWN
Classifier: Development Status :: 5 - Production/Stable
Classifier: Environment :: Console
Classifier: Intended Audience :: Science/Research
Classifier: Topic :: Scientific/Engineering :: Artificial Intelligence
Classifier: License :: OSI Approved :: MIT License
Classifier: Natural Language :: English
Classifier: Programming Language :: Python :: 3.6
